{
  "status": "live",
  "started_at": "2026-03-07T12:15:25.249600+00:00",
  "updated_at": "2026-03-08T01:06:34.633572+00:00",
  "uptime_seconds": 46269.4,
  "method": "M4",
  "strategy": {
    "method": "M4",
    "entry_params": {
      "drop1_fib": 0.786,
      "rev1_ratio": 0.5,
      "drop2_fib": 0.236
    },
    "source": "backtest",
    "sl_pct": 29,
    "tp_pct": 140,
    "trailing_activation_pct": 100,
    "trailing_pct": 5,
    "mcap_min": 30000,
    "mcap_max": 1000000,
    "gates_passed": 1,
    "all_11_passed": false,
    "backtest_avg_pnl": -7.1804,
    "backtest_win_rate": 19.35483870967742,
    "backtest_sortino": -8.985,
    "backtest_n_trades": 62,
    "post_entry_filters": {}
  },
  "dry_run": false,
  "terminal": [
    "[00:59:26] \ud83d\udcca Mig:2383 Track:126 Upd:1071551 Pos:0 SOL:$83.01",
    "[00:59:34] \ud83d\udd14 Migration #2384 detected",
    "[01:00:00] \ud83d\udd14 Migration #2385 detected",
    "[01:00:19] \ud83d\udd14 Migration #2386 detected",
    "[01:00:24] \ud83d\udd14 Migration #2387 detected",
    "[01:00:27] \ud83d\udcca Mig:2387 Track:126 Upd:1072950 Pos:0 SOL:$83.03",
    "[01:00:28] \ud83d\udee1\ufe0f Signal gate: 38p1gZEuoVah\u2026 | top5=55.8%>40%",
    "[01:00:28] \ud83d\udeab Disqualified: 38p1gZEuoVah\u2026 | signal_gate_failed | 20.2m",
    "[01:00:28] \ud83d\udd14 Migration #2388 detected",
    "[01:00:32] \u2705 BC Graduated: DXJhN4tKkwGW\u2026",
    "[01:00:32] \ud83d\udce1 Tracking: DXJhN4tKkwGWrAiw\u2026 | Pool #126",
    "[01:00:49] \ud83d\udd14 Migration #2389 detected",
    "[01:01:10] \ud83d\udd14 Migration #2390 detected",
    "[01:01:28] \ud83d\udcca Mig:2390 Track:126 Upd:1074263 Pos:0 SOL:$83.04",
    "[01:01:51] \ud83d\udd14 Migration #2391 detected",
    "[01:02:25] \ud83d\udd14 Migration #2392 detected",
    "[01:02:29] \ud83d\udcca Mig:2392 Track:126 Upd:1075645 Pos:0 SOL:$83.04",
    "[01:02:55] \ud83d\udd14 Migration #2393 detected",
    "[01:03:00] \ud83d\udd14 Migration #2394 detected",
    "[01:03:01] \ud83d\udd14 Migration #2395 detected",
    "[01:03:05] \ud83d\udd14 Migration #2396 detected",
    "[01:03:09] \ud83d\udd14 Migration #2397 detected",
    "[01:03:10] \ud83d\udd14 Migration #2398 detected",
    "[01:03:11] \ud83d\udd14 Migration #2399 detected",
    "[01:03:14] \ud83d\udd14 Migration #2400 detected",
    "[01:03:18] \ud83d\udd14 Migration #2401 detected",
    "[01:03:19] \ud83d\udd14 Migration #2402 detected",
    "[01:03:22] \ud83d\udd14 Migration #2403 detected",
    "[01:03:24] \ud83d\udd14 Migration #2404 detected",
    "[01:03:28] \ud83d\udd14 Migration #2405 detected",
    "[01:03:28] \ud83d\udd14 Migration #2406 detected",
    "[01:03:31] \ud83d\udcca Mig:2406 Track:126 Upd:1077059 Pos:0 SOL:$83.04",
    "[01:04:15] \ud83d\udd14 Migration #2407 detected",
    "[01:04:22] \ud83d\udd14 Migration #2408 detected",
    "[01:04:32] \ud83d\udcca Mig:2408 Track:126 Upd:1078470 Pos:0 SOL:$83.03",
    "[01:04:48] \ud83d\udd14 Migration #2409 detected",
    "[01:05:33] \ud83d\udcca Mig:2409 Track:126 Upd:1079761 Pos:0 SOL:$83.02",
    "[01:05:56] \ud83d\udd14 Migration #2410 detected",
    "[01:06:31] \ud83d\udd14 Migration #2411 detected",
    "[01:06:34] \ud83d\udcca Mig:2411 Track:126 Upd:1081009 Pos:0 SOL:$83.02"
  ],
  "balance": {
    "start": 4.077029,
    "current": 3.826566,
    "pnl_sol": -0.250463,
    "pnl_pct": -6.14
  },
  "trades": {
    "total": 0,
    "wins": 0,
    "losses": 0,
    "win_rate": 0
  },
  "positions": {
    "open": 0
  },
  "sol_price": 83.02,
  "bot_stats": {
    "migrations_seen": 2411,
    "migrations_added": 149,
    "pools_tracking": 126,
    "price_updates": 1081009,
    "migrations_rejected": 0,
    "liquidity_rejected": 4,
    "bc_graduated": 153,
    "entries_found": 0,
    "buys_success": 0,
    "buys_failed": 0
  }
}