{
  "status": "live",
  "started_at": "2026-03-07T12:15:25.249600+00:00",
  "updated_at": "2026-03-07T22:04:22.402305+00:00",
  "uptime_seconds": 35337.2,
  "method": "M4",
  "strategy": {
    "method": "M4",
    "entry_params": {
      "drop1_fib": 0.786,
      "rev1_ratio": 0.5,
      "drop2_fib": 0.236
    },
    "source": "backtest",
    "sl_pct": 29,
    "tp_pct": 140,
    "trailing_activation_pct": 100,
    "trailing_pct": 5,
    "mcap_min": 30000,
    "mcap_max": 1000000,
    "gates_passed": 1,
    "all_11_passed": false,
    "backtest_avg_pnl": -7.1804,
    "backtest_win_rate": 19.35483870967742,
    "backtest_sortino": -8.985,
    "backtest_n_trades": 62,
    "post_entry_filters": {}
  },
  "dry_run": false,
  "terminal": [
    "[21:54:11] \ud83d\udcca Mig:1866 Track:108 Upd:760235 Pos:0 SOL:$83.06",
    "[21:54:34] \ud83d\udd14 Migration #1867 detected",
    "[21:55:12] \ud83d\udcca Mig:1867 Track:108 Upd:762367 Pos:0 SOL:$83.07",
    "[21:55:29] \ud83d\udd14 Migration #1868 detected",
    "[21:55:54] \ud83d\udd14 Migration #1869 detected",
    "[21:56:13] \ud83d\udcca Mig:1869 Track:108 Upd:764518 Pos:0 SOL:$83.07",
    "[21:57:13] \ud83d\udd14 Migration #1870 detected",
    "[21:57:14] \ud83d\udcca Mig:1870 Track:108 Upd:766725 Pos:0 SOL:$83.08",
    "[21:57:14] \ud83d\udd14 Migration #1871 detected",
    "[21:57:18] \ud83d\udd14 Migration #1872 detected",
    "[21:57:45] \ud83d\udd14 Migration #1873 detected",
    "[21:58:03] \ud83d\udd14 Migration #1874 detected",
    "[21:58:15] \ud83d\udcca Mig:1874 Track:108 Upd:768941 Pos:0 SOL:$83.10",
    "[21:58:35] \ud83d\udd14 Migration #1875 detected",
    "[21:58:58] \ud83d\udd14 Migration #1876 detected",
    "[21:59:02] \ud83d\udd14 Migration #1877 detected",
    "[21:59:16] \ud83d\udcca Mig:1877 Track:108 Upd:770923 Pos:0 SOL:$83.12",
    "[21:59:24] \ud83d\udd14 Migration #1878 detected",
    "[21:59:37] \u2705 BC Graduated: ATkaxFrmx3ox\u2026",
    "[21:59:37] \ud83d\udca7 Liquidity rejected: 8.8 SOL < 15.0 SOL",
    "[21:59:40] \ud83d\udd14 Migration #1879 detected",
    "[22:00:17] \ud83d\udcca Mig:1879 Track:108 Upd:773072 Pos:0 SOL:$83.15",
    "[22:00:29] \ud83d\udd14 Migration #1880 detected",
    "[22:00:49] \ud83d\udd14 Migration #1881 detected",
    "[22:01:06] \ud83d\udd14 Migration #1882 detected",
    "[22:01:19] \ud83d\udcca Mig:1882 Track:108 Upd:775138 Pos:0 SOL:$83.16",
    "[22:01:33] \ud83d\udd14 Migration #1883 detected",
    "[22:01:33] \ud83d\udd14 Migration #1884 detected",
    "[22:02:15] \ud83d\udd14 Migration #1885 detected",
    "[22:02:20] \ud83d\udcca Mig:1885 Track:108 Upd:777220 Pos:0 SOL:$83.16",
    "[22:02:52] \ud83d\udd14 Migration #1886 detected",
    "[22:03:21] \ud83d\udcca Mig:1886 Track:108 Upd:779336 Pos:0 SOL:$83.17",
    "[22:03:48] \ud83d\udd14 Migration #1887 detected",
    "[22:03:51] \ud83d\udd14 Migration #1888 detected",
    "[22:04:03] \ud83d\udd14 Migration #1889 detected",
    "[22:04:17] \u2705 BC Graduated: GtAHbD7JD7xQ\u2026",
    "[22:04:17] \ud83d\udce1 Tracking: GtAHbD7JD7xQJW9a\u2026 | Pool #109",
    "[22:04:18] \ud83d\udd14 Migration #1890 detected",
    "[22:04:19] \ud83d\udd14 Migration #1891 detected",
    "[22:04:22] \ud83d\udcca Mig:1891 Track:109 Upd:781374 Pos:0 SOL:$83.19"
  ],
  "balance": {
    "start": 4.077029,
    "current": 3.826566,
    "pnl_sol": -0.250463,
    "pnl_pct": -6.14
  },
  "trades": {
    "total": 0,
    "wins": 0,
    "losses": 0,
    "win_rate": 0
  },
  "positions": {
    "open": 0
  },
  "sol_price": 83.19,
  "bot_stats": {
    "migrations_seen": 1891,
    "migrations_added": 124,
    "pools_tracking": 109,
    "price_updates": 781374,
    "migrations_rejected": 0,
    "liquidity_rejected": 2,
    "bc_graduated": 126,
    "entries_found": 0,
    "buys_success": 0,
    "buys_failed": 0
  }
}