{
  "status": "live",
  "started_at": "2026-03-04T12:27:15.748276+00:00",
  "updated_at": "2026-03-04T18:49:47.158641+00:00",
  "uptime_seconds": 22951.4,
  "method": "M4",
  "strategy": {
    "method": "M4",
    "entry_params": {
      "drop1_fib": 0.786,
      "rev1_ratio": 0.618,
      "drop2_fib": 0.786
    },
    "source": "backtest",
    "sl_pct": 23,
    "tp_pct": 110,
    "trailing_activation_pct": 100,
    "trailing_pct": 5,
    "mcap_min": 10000,
    "mcap_max": 1000000,
    "gates_passed": 4,
    "all_11_passed": false,
    "backtest_avg_pnl": 6.5592,
    "backtest_win_rate": 21.73913043478261,
    "backtest_sortino": 12.54,
    "backtest_n_trades": 46,
    "post_entry_filters": {
      "PERF_10S": {
        "LT_MINUS15": {
          "keep": true,
          "lift": 1.0,
          "count": 3,
          "avg_exit": 0,
          "avg_hold": 0,
          "advantage": 0
        },
        "MINUS15_MINUS5": {
          "keep": true,
          "lift": 1.0,
          "count": 7,
          "avg_exit": 0,
          "avg_hold": 0,
          "advantage": 0
        },
        "MINUS5_0": {
          "keep": true,
          "lift": 1.029,
          "count": 22,
          "avg_exit": -7.52,
          "avg_hold": 3.0,
          "advantage": -10.51
        },
        "0_PLUS5": {
          "keep": true,
          "lift": 1.0,
          "count": 13,
          "avg_exit": 0,
          "avg_hold": 0,
          "advantage": 0
        },
        "PLUS5_PLUS15": {
          "keep": true,
          "lift": 1.0,
          "count": 12,
          "avg_exit": 0,
          "avg_hold": 0,
          "advantage": 0
        },
        "PLUS15_PLUS30": {
          "keep": true,
          "lift": 1.0,
          "count": 4,
          "avg_exit": 0,
          "avg_hold": 0,
          "advantage": 0
        },
        "GT_PLUS30": {
          "keep": true,
          "lift": 1.0,
          "count": 2,
          "avg_exit": 0,
          "avg_hold": 0,
          "advantage": 0
        }
      },
      "PERF_30S": {
        "LT_MINUS20": {
          "keep": true,
          "lift": 1.0,
          "count": 5,
          "avg_exit": 0,
          "avg_hold": 0,
          "advantage": 0
        },
        "MINUS20_MINUS10": {
          "keep": true,
          "lift": 1.0,
          "count": 5,
          "avg_exit": 0,
          "avg_hold": 0,
          "advantage": 0
        },
        "MINUS10_0": {
          "keep": true,
          "lift": 0.618,
          "count": 20,
          "avg_exit": -9.32,
          "avg_hold": -7.65,
          "advantage": -1.68
        },
        "0_PLUS10": {
          "keep": true,
          "lift": 1.615,
          "count": 19,
          "avg_exit": 3.66,
          "avg_hold": 15.18,
          "advantage": -11.53
        },
        "PLUS10_PLUS25": {
          "keep": true,
          "lift": 1.0,
          "count": 9,
          "avg_exit": 0,
          "avg_hold": 0,
          "advantage": 0
        },
        "PLUS25_PLUS50": {
          "keep": true,
          "lift": 1.0,
          "count": 2,
          "avg_exit": 0,
          "avg_hold": 0,
          "advantage": 0
        },
        "GT_PLUS50": {
          "keep": true,
          "lift": 1.0,
          "count": 3,
          "avg_exit": 0,
          "avg_hold": 0,
          "advantage": 0
        }
      },
      "PERF_60S": {
        "LT_MINUS30": {
          "keep": true,
          "lift": 1.0,
          "count": 6,
          "avg_exit": 0,
          "avg_hold": 0,
          "advantage": 0
        },
        "MINUS30_MINUS15": {
          "keep": true,
          "lift": 1.0,
          "count": 5,
          "avg_exit": 0,
          "avg_hold": 0,
          "advantage": 0
        },
        "MINUS15_0": {
          "keep": false,
          "lift": 0.184,
          "count": 20,
          "avg_exit": -11.52,
          "avg_hold": -21.41,
          "advantage": 9.9
        },
        "0_PLUS15": {
          "keep": true,
          "lift": 1.885,
          "count": 20,
          "avg_exit": 4.53,
          "avg_hold": 19.9,
          "advantage": -15.36
        },
        "PLUS15_PLUS40": {
          "keep": true,
          "lift": 1.0,
          "count": 9,
          "avg_exit": 0,
          "avg_hold": 0,
          "advantage": 0
        },
        "PLUS40_PLUS80": {
          "keep": true,
          "lift": 1.0,
          "count": 3,
          "avg_exit": 0,
          "avg_hold": 0,
          "advantage": 0
        },
        "GT_PLUS80": {
          "keep": true,
          "lift": 1.0,
          "count": 0,
          "avg_exit": 0,
          "avg_hold": 0,
          "advantage": 0
        }
      },
      "PERF_5M": {
        "LT_MINUS50": {
          "keep": true,
          "lift": 1.0,
          "count": 8,
          "avg_exit": 0,
          "avg_hold": 0,
          "advantage": 0
        },
        "MINUS50_MINUS30": {
          "keep": true,
          "lift": 1.0,
          "count": 7,
          "avg_exit": 0,
          "avg_hold": 0,
          "advantage": 0
        },
        "MINUS30_MINUS15": {
          "keep": true,
          "lift": 1.0,
          "count": 2,
          "avg_exit": 0,
          "avg_hold": 0,
          "advantage": 0
        },
        "MINUS15_0": {
          "keep": true,
          "lift": 1.0,
          "count": 8,
          "avg_exit": 0,
          "avg_hold": 0,
          "advantage": 0
        },
        "0_PLUS25": {
          "keep": true,
          "lift": 1.0,
          "count": 11,
          "avg_exit": 0,
          "avg_hold": 0,
          "advantage": 0
        },
        "PLUS25_PLUS50": {
          "keep": true,
          "lift": 1.0,
          "count": 4,
          "avg_exit": 0,
          "avg_hold": 0,
          "advantage": 0
        },
        "PLUS50_PLUS100": {
          "keep": true,
          "lift": 1.0,
          "count": 2,
          "avg_exit": 0,
          "avg_hold": 0,
          "advantage": 0
        },
        "PLUS100_PLUS200": {
          "keep": true,
          "lift": 1.0,
          "count": 0,
          "avg_exit": 0,
          "avg_hold": 0,
          "advantage": 0
        },
        "GT_PLUS200": {
          "keep": true,
          "lift": 1.0,
          "count": 1,
          "avg_exit": 0,
          "avg_hold": 0,
          "advantage": 0
        }
      },
      "PERF_10M": {
        "LT_MINUS60": {
          "keep": true,
          "lift": 1.0,
          "count": 9,
          "avg_exit": 0,
          "avg_hold": 0,
          "advantage": 0
        },
        "MINUS60_MINUS40": {
          "keep": true,
          "lift": 1.0,
          "count": 3,
          "avg_exit": 0,
          "avg_hold": 0,
          "advantage": 0
        },
        "MINUS40_MINUS20": {
          "keep": true,
          "lift": 1.0,
          "count": 3,
          "avg_exit": 0,
          "avg_hold": 0,
          "advantage": 0
        },
        "MINUS20_0": {
          "keep": true,
          "lift": 1.0,
          "count": 11,
          "avg_exit": 0,
          "avg_hold": 0,
          "advantage": 0
        },
        "0_PLUS30": {
          "keep": true,
          "lift": 1.0,
          "count": 8,
          "avg_exit": 0,
          "avg_hold": 0,
          "advantage": 0
        },
        "PLUS30_PLUS75": {
          "keep": true,
          "lift": 1.0,
          "count": 7,
          "avg_exit": 0,
          "avg_hold": 0,
          "advantage": 0
        },
        "PLUS75_PLUS150": {
          "keep": true,
          "lift": 1.0,
          "count": 2,
          "avg_exit": 0,
          "avg_hold": 0,
          "advantage": 0
        },
        "PLUS150_PLUS300": {
          "keep": true,
          "lift": 1.0,
          "count": 0,
          "avg_exit": 0,
          "avg_hold": 0,
          "advantage": 0
        },
        "GT_PLUS300": {
          "keep": true,
          "lift": 1.0,
          "count": 0,
          "avg_exit": 0,
          "avg_hold": 0,
          "advantage": 0
        }
      },
      "DELTA_10S_30S": {
        "LT_MINUS20": {
          "keep": true,
          "lift": 1.0,
          "count": 1,
          "avg_exit": 0,
          "avg_hold": 0,
          "advantage": 0
        },
        "MINUS20_MINUS10": {
          "keep": true,
          "lift": 1.0,
          "count": 5,
          "avg_exit": 0,
          "avg_hold": 0,
          "advantage": 0
        },
        "MINUS10_MINUS3": {
          "keep": true,
          "lift": 1.0,
          "count": 7,
          "avg_exit": 0,
          "avg_hold": 0,
          "advantage": 0
        },
        "MINUS3_PLUS3": {
          "keep": true,
          "lift": 1.154,
          "count": 15,
          "avg_exit": 2.92,
          "avg_hold": 17.6,
          "advantage": -14.68
        },
        "PLUS3_PLUS10": {
          "keep": true,
          "lift": 1.0,
          "count": 8,
          "avg_exit": 0,
          "avg_hold": 0,
          "advantage": 0
        },
        "PLUS10_PLUS20": {
          "keep": true,
          "lift": 1.0,
          "count": 4,
          "avg_exit": 0,
          "avg_hold": 0,
          "advantage": 0
        },
        "GT_PLUS20": {
          "keep": true,
          "lift": 1.0,
          "count": 3,
          "avg_exit": 0,
          "avg_hold": 0,
          "advantage": 0
        }
      },
      "DELTA_30S_60S": {
        "LT_MINUS25": {
          "keep": true,
          "lift": 1.0,
          "count": 5,
          "avg_exit": 0,
          "avg_hold": 0,
          "advantage": 0
        },
        "MINUS25_MINUS10": {
          "keep": true,
          "lift": 1.0,
          "count": 5,
          "avg_exit": 0,
          "avg_hold": 0,
          "advantage": 0
        },
        "MINUS10_MINUS3": {
          "keep": true,
          "lift": 1.0,
          "count": 6,
          "avg_exit": 0,
          "avg_hold": 0,
          "advantage": 0
        },
        "MINUS3_PLUS3": {
          "keep": true,
          "lift": 1.0,
          "count": 12,
          "avg_exit": 0,
          "avg_hold": 0,
          "advantage": 0
        },
        "PLUS3_PLUS10": {
          "keep": true,
          "lift": 1.0,
          "count": 8,
          "avg_exit": 0,
          "avg_hold": 0,
          "advantage": 0
        },
        "PLUS10_PLUS25": {
          "keep": true,
          "lift": 1.0,
          "count": 4,
          "avg_exit": 0,
          "avg_hold": 0,
          "advantage": 0
        },
        "GT_PLUS25": {
          "keep": true,
          "lift": 1.0,
          "count": 3,
          "avg_exit": 0,
          "avg_hold": 0,
          "advantage": 0
        }
      },
      "DELTA_60S_5M": {
        "LT_MINUS40": {
          "keep": true,
          "lift": 1.0,
          "count": 11,
          "avg_exit": 0,
          "avg_hold": 0,
          "advantage": 0
        },
        "MINUS40_MINUS20": {
          "keep": true,
          "lift": 1.0,
          "count": 2,
          "avg_exit": 0,
          "avg_hold": 0,
          "advantage": 0
        },
        "MINUS20_MINUS5": {
          "keep": true,
          "lift": 1.0,
          "count": 5,
          "avg_exit": 0,
          "avg_hold": 0,
          "advantage": 0
        },
        "MINUS5_PLUS5": {
          "keep": true,
          "lift": 1.0,
          "count": 11,
          "avg_exit": 0,
          "avg_hold": 0,
          "advantage": 0
        },
        "PLUS5_PLUS20": {
          "keep": true,
          "lift": 1.0,
          "count": 8,
          "avg_exit": 0,
          "avg_hold": 0,
          "advantage": 0
        },
        "PLUS20_PLUS50": {
          "keep": true,
          "lift": 1.0,
          "count": 4,
          "avg_exit": 0,
          "avg_hold": 0,
          "advantage": 0
        },
        "GT_PLUS50": {
          "keep": true,
          "lift": 1.0,
          "count": 2,
          "avg_exit": 0,
          "avg_hold": 0,
          "advantage": 0
        }
      }
    }
  },
  "dry_run": false,
  "terminal": [
    "[18:39:29] \ud83d\udd14 Migration #1067 detected",
    "[18:39:50] \ud83d\udd14 Migration #1068 detected",
    "[18:39:51] \ud83d\udcca Mig:1068 Track:79 Upd:444712 Pos:0 SOL:$91.83",
    "[18:40:30] \ud83d\udd14 Migration #1069 detected",
    "[18:40:38] \ud83d\udd14 Migration #1070 detected",
    "[18:40:39] \ud83d\udd14 Migration #1071 detected",
    "[18:40:39] \ud83d\udd14 Migration #1072 detected",
    "[18:40:50] \ud83d\udd14 Migration #1073 detected",
    "[18:40:52] \ud83d\udcca Mig:1073 Track:79 Upd:447272 Pos:0 SOL:$91.81",
    "[18:41:51] \ud83d\udd14 Migration #1074 detected",
    "[18:41:54] \ud83d\udcca Mig:1074 Track:79 Upd:449758 Pos:0 SOL:$91.81",
    "[18:42:55] \ud83d\udcca Mig:1074 Track:79 Upd:452239 Pos:0 SOL:$91.85",
    "[18:42:58] \ud83d\udd14 Migration #1075 detected",
    "[18:43:11] \u2705 BC Graduated: Eio6hKvVUvQK\u2026",
    "[18:43:12] \ud83d\udce1 Tracking: Eio6hKvVUvQKZhBt\u2026 | Pool #80",
    "[18:43:34] \ud83d\udd14 Migration #1076 detected",
    "[18:43:49] \ud83d\udd14 Migration #1077 detected",
    "[18:43:56] \ud83d\udcca Mig:1077 Track:80 Upd:454738 Pos:0 SOL:$91.88",
    "[18:44:20] \ud83d\udd14 Migration #1078 detected",
    "[18:44:33] \u2705 BC Graduated: 4r5XXx8vtY6i\u2026",
    "[18:44:34] \ud83d\udce1 Tracking: 4r5XXx8vtY6iU98y\u2026 | Pool #81",
    "[18:44:57] \ud83d\udcca Mig:1078 Track:81 Upd:457284 Pos:0 SOL:$91.89",
    "[18:45:56] \ud83d\udd14 Migration #1079 detected",
    "[18:45:58] \ud83d\udcca Mig:1079 Track:81 Upd:459817 Pos:0 SOL:$91.89",
    "[18:45:59] \ud83d\udd14 Migration #1080 detected",
    "[18:46:02] \ud83d\udd14 Migration #1081 detected",
    "[18:46:11] \ud83d\udd14 Migration #1082 detected",
    "[18:46:59] \ud83d\udcca Mig:1082 Track:81 Upd:462046 Pos:0 SOL:$91.96",
    "[18:47:28] \ud83d\udd14 Migration #1083 detected",
    "[18:47:40] \ud83d\udd14 Migration #1084 detected",
    "[18:47:43] \ud83d\udd14 Migration #1085 detected",
    "[18:47:55] \ud83d\udd14 Migration #1086 detected",
    "[18:48:00] \ud83d\udcca Mig:1086 Track:81 Upd:464475 Pos:0 SOL:$92.01",
    "[18:48:14] \ud83d\udd14 Migration #1087 detected",
    "[18:48:34] \ud83d\udd14 Migration #1088 detected",
    "[18:48:38] \ud83d\udd14 Migration #1089 detected",
    "[18:49:01] \ud83d\udcca Mig:1089 Track:81 Upd:466647 Pos:0 SOL:$92.02",
    "[18:49:09] \ud83d\udd14 Migration #1090 detected",
    "[18:49:11] \ud83d\udd14 Migration #1091 detected",
    "[18:49:31] \ud83d\udd14 Migration #1092 detected"
  ],
  "balance": {
    "start": 4.06455,
    "current": 4.451714,
    "pnl_sol": 0.387165,
    "pnl_pct": 9.53
  },
  "trades": {
    "total": 2,
    "wins": 0,
    "losses": 2,
    "win_rate": 0.0
  },
  "positions": {
    "open": 0
  },
  "sol_price": 92.05,
  "bot_stats": {
    "migrations_seen": 1092,
    "migrations_added": 84,
    "pools_tracking": 81,
    "price_updates": 468254,
    "migrations_rejected": 0,
    "liquidity_rejected": 0,
    "bc_graduated": 84,
    "entries_found": 2,
    "buys_success": 2,
    "buys_failed": 0
  }
}