{
  "status": "live",
  "started_at": "2026-03-08T13:53:32.945026+00:00",
  "updated_at": "2026-03-09T05:45:16.304458+00:00",
  "uptime_seconds": 57103.4,
  "method": "ENV",
  "strategy": {},
  "dry_run": false,
  "terminal": [
    "[05:37:16] \ud83d\udd14 Migration #2945 detected",
    "[05:37:44] \ud83d\udd14 Migration #2946 detected",
    "[05:37:58] \ud83d\udd14 Migration #2947 detected",
    "[05:38:17] \ud83d\udd14 Migration #2948 detected",
    "[05:38:17] \ud83d\udcca Mig:2948 Track:0 Upd:41930 Pos:0 SOL:$83.64",
    "[05:38:20] \ud83d\udd14 Migration #2949 detected",
    "[05:38:46] \ud83d\udd14 Migration #2950 detected",
    "[05:39:14] \ud83d\udd14 Migration #2951 detected",
    "[05:39:18] \ud83d\udcca Mig:2951 Track:0 Upd:41930 Pos:0 SOL:$83.63",
    "[05:39:25] \ud83d\udd14 Migration #2952 detected",
    "[05:39:32] \ud83d\udd14 Migration #2953 detected",
    "[05:40:17] \ud83d\udd14 Migration #2954 detected",
    "[05:40:20] \ud83d\udcca Mig:2954 Track:0 Upd:41930 Pos:0 SOL:$83.62",
    "[05:41:10] \ud83d\udd14 Migration #2955 detected",
    "[05:41:21] \ud83d\udcca Mig:2955 Track:0 Upd:41930 Pos:0 SOL:$83.64",
    "[05:41:44] \ud83d\udd14 Migration #2956 detected",
    "[05:42:17] \ud83d\udd14 Migration #2957 detected",
    "[05:42:22] \ud83d\udcca Mig:2957 Track:0 Upd:41930 Pos:0 SOL:$83.67",
    "[05:42:27] \ud83d\udd14 Migration #2958 detected",
    "[05:42:27] \ud83d\udd14 Migration #2959 detected",
    "[05:42:31] \ud83d\udd14 Migration #2960 detected",
    "[05:42:35] \ud83d\udd14 Migration #2961 detected",
    "[05:42:51] \ud83d\udd14 Migration #2962 detected",
    "[05:43:03] \ud83d\udd14 Migration #2963 detected",
    "[05:43:03] \ud83d\udd14 Migration #2964 detected",
    "[05:43:09] \ud83d\udd14 Migration #2965 detected",
    "[05:43:23] \ud83d\udcca Mig:2965 Track:0 Upd:41930 Pos:0 SOL:$83.74",
    "[05:43:26] \ud83d\udd14 Migration #2966 detected",
    "[05:43:37] \ud83d\udd14 Migration #2967 detected",
    "[05:43:39] \ud83d\udd14 Migration #2968 detected",
    "[05:43:39] \u2705 BC Graduated: 8ZZqArRqyCcK\u2026",
    "[05:43:40] \ud83d\udce1 Tracking: 8ZZqArRqyCcKojpE\u2026 | Pool #1",
    "[05:44:14] \ud83d\udd14 Migration #2969 detected",
    "[05:44:14] \ud83d\udd14 Migration #2970 detected",
    "[05:44:24] \ud83d\udcca Mig:2970 Track:1 Upd:42059 Pos:0 SOL:$83.82",
    "[05:44:30] \ud83d\udd14 Migration #2971 detected",
    "[05:44:41] \ud83d\udeab Disqualified: 8ZZqArRqyCcK\u2026 | max_time_without_entry | 1.0m",
    "[05:44:57] \ud83d\udd14 Migration #2972 detected",
    "[05:45:07] \ud83d\udd14 Migration #2973 detected",
    "[05:45:12] \ud83d\udd14 Migration #2974 detected"
  ],
  "balance": {
    "start": 3.826566,
    "current": 3.284376,
    "pnl_sol": -0.54219,
    "pnl_pct": -14.17
  },
  "trades": {
    "total": 0,
    "wins": 0,
    "losses": 0,
    "win_rate": 0
  },
  "positions": {
    "open": 0
  },
  "sol_price": 83.85,
  "bot_stats": {
    "migrations_seen": 2974,
    "migrations_added": 195,
    "pools_tracking": 0,
    "price_updates": 42105,
    "migrations_rejected": 0,
    "liquidity_rejected": 7,
    "bc_graduated": 202,
    "entries_found": 0,
    "buys_success": 0,
    "buys_failed": 0
  }
}