{
  "status": "live",
  "started_at": "2026-03-03T19:41:40.501776+00:00",
  "updated_at": "2026-03-04T03:10:34.913292+00:00",
  "uptime_seconds": 26934.4,
  "method": "M4",
  "strategy": {
    "method": "M4",
    "entry_params": {
      "drop1_fib": 0.786,
      "rev1_ratio": 0.618,
      "drop2_fib": 0.786
    },
    "source": "backtest",
    "sl_pct": 23,
    "tp_pct": 110,
    "trailing_activation_pct": 100,
    "trailing_pct": 5,
    "mcap_min": 10000,
    "mcap_max": 1000000,
    "gates_passed": 4,
    "all_11_passed": false,
    "backtest_avg_pnl": 6.5592,
    "backtest_win_rate": 21.73913043478261,
    "backtest_sortino": 12.54,
    "backtest_n_trades": 46,
    "post_entry_filters": {
      "PERF_10S": {
        "LT_MINUS15": {
          "keep": true,
          "lift": 1.0,
          "count": 3,
          "avg_exit": 0,
          "avg_hold": 0,
          "advantage": 0
        },
        "MINUS15_MINUS5": {
          "keep": true,
          "lift": 1.0,
          "count": 7,
          "avg_exit": 0,
          "avg_hold": 0,
          "advantage": 0
        },
        "MINUS5_0": {
          "keep": true,
          "lift": 1.029,
          "count": 22,
          "avg_exit": -7.52,
          "avg_hold": 3.0,
          "advantage": -10.51
        },
        "0_PLUS5": {
          "keep": true,
          "lift": 1.0,
          "count": 13,
          "avg_exit": 0,
          "avg_hold": 0,
          "advantage": 0
        },
        "PLUS5_PLUS15": {
          "keep": true,
          "lift": 1.0,
          "count": 12,
          "avg_exit": 0,
          "avg_hold": 0,
          "advantage": 0
        },
        "PLUS15_PLUS30": {
          "keep": true,
          "lift": 1.0,
          "count": 4,
          "avg_exit": 0,
          "avg_hold": 0,
          "advantage": 0
        },
        "GT_PLUS30": {
          "keep": true,
          "lift": 1.0,
          "count": 2,
          "avg_exit": 0,
          "avg_hold": 0,
          "advantage": 0
        }
      },
      "PERF_30S": {
        "LT_MINUS20": {
          "keep": true,
          "lift": 1.0,
          "count": 5,
          "avg_exit": 0,
          "avg_hold": 0,
          "advantage": 0
        },
        "MINUS20_MINUS10": {
          "keep": true,
          "lift": 1.0,
          "count": 5,
          "avg_exit": 0,
          "avg_hold": 0,
          "advantage": 0
        },
        "MINUS10_0": {
          "keep": true,
          "lift": 0.618,
          "count": 20,
          "avg_exit": -9.32,
          "avg_hold": -7.65,
          "advantage": -1.68
        },
        "0_PLUS10": {
          "keep": true,
          "lift": 1.615,
          "count": 19,
          "avg_exit": 3.66,
          "avg_hold": 15.18,
          "advantage": -11.53
        },
        "PLUS10_PLUS25": {
          "keep": true,
          "lift": 1.0,
          "count": 9,
          "avg_exit": 0,
          "avg_hold": 0,
          "advantage": 0
        },
        "PLUS25_PLUS50": {
          "keep": true,
          "lift": 1.0,
          "count": 2,
          "avg_exit": 0,
          "avg_hold": 0,
          "advantage": 0
        },
        "GT_PLUS50": {
          "keep": true,
          "lift": 1.0,
          "count": 3,
          "avg_exit": 0,
          "avg_hold": 0,
          "advantage": 0
        }
      },
      "PERF_60S": {
        "LT_MINUS30": {
          "keep": true,
          "lift": 1.0,
          "count": 6,
          "avg_exit": 0,
          "avg_hold": 0,
          "advantage": 0
        },
        "MINUS30_MINUS15": {
          "keep": true,
          "lift": 1.0,
          "count": 5,
          "avg_exit": 0,
          "avg_hold": 0,
          "advantage": 0
        },
        "MINUS15_0": {
          "keep": false,
          "lift": 0.184,
          "count": 20,
          "avg_exit": -11.52,
          "avg_hold": -21.41,
          "advantage": 9.9
        },
        "0_PLUS15": {
          "keep": true,
          "lift": 1.885,
          "count": 20,
          "avg_exit": 4.53,
          "avg_hold": 19.9,
          "advantage": -15.36
        },
        "PLUS15_PLUS40": {
          "keep": true,
          "lift": 1.0,
          "count": 9,
          "avg_exit": 0,
          "avg_hold": 0,
          "advantage": 0
        },
        "PLUS40_PLUS80": {
          "keep": true,
          "lift": 1.0,
          "count": 3,
          "avg_exit": 0,
          "avg_hold": 0,
          "advantage": 0
        },
        "GT_PLUS80": {
          "keep": true,
          "lift": 1.0,
          "count": 0,
          "avg_exit": 0,
          "avg_hold": 0,
          "advantage": 0
        }
      },
      "PERF_5M": {
        "LT_MINUS50": {
          "keep": true,
          "lift": 1.0,
          "count": 8,
          "avg_exit": 0,
          "avg_hold": 0,
          "advantage": 0
        },
        "MINUS50_MINUS30": {
          "keep": true,
          "lift": 1.0,
          "count": 7,
          "avg_exit": 0,
          "avg_hold": 0,
          "advantage": 0
        },
        "MINUS30_MINUS15": {
          "keep": true,
          "lift": 1.0,
          "count": 2,
          "avg_exit": 0,
          "avg_hold": 0,
          "advantage": 0
        },
        "MINUS15_0": {
          "keep": true,
          "lift": 1.0,
          "count": 8,
          "avg_exit": 0,
          "avg_hold": 0,
          "advantage": 0
        },
        "0_PLUS25": {
          "keep": true,
          "lift": 1.0,
          "count": 11,
          "avg_exit": 0,
          "avg_hold": 0,
          "advantage": 0
        },
        "PLUS25_PLUS50": {
          "keep": true,
          "lift": 1.0,
          "count": 4,
          "avg_exit": 0,
          "avg_hold": 0,
          "advantage": 0
        },
        "PLUS50_PLUS100": {
          "keep": true,
          "lift": 1.0,
          "count": 2,
          "avg_exit": 0,
          "avg_hold": 0,
          "advantage": 0
        },
        "PLUS100_PLUS200": {
          "keep": true,
          "lift": 1.0,
          "count": 0,
          "avg_exit": 0,
          "avg_hold": 0,
          "advantage": 0
        },
        "GT_PLUS200": {
          "keep": true,
          "lift": 1.0,
          "count": 1,
          "avg_exit": 0,
          "avg_hold": 0,
          "advantage": 0
        }
      },
      "PERF_10M": {
        "LT_MINUS60": {
          "keep": true,
          "lift": 1.0,
          "count": 9,
          "avg_exit": 0,
          "avg_hold": 0,
          "advantage": 0
        },
        "MINUS60_MINUS40": {
          "keep": true,
          "lift": 1.0,
          "count": 3,
          "avg_exit": 0,
          "avg_hold": 0,
          "advantage": 0
        },
        "MINUS40_MINUS20": {
          "keep": true,
          "lift": 1.0,
          "count": 3,
          "avg_exit": 0,
          "avg_hold": 0,
          "advantage": 0
        },
        "MINUS20_0": {
          "keep": true,
          "lift": 1.0,
          "count": 11,
          "avg_exit": 0,
          "avg_hold": 0,
          "advantage": 0
        },
        "0_PLUS30": {
          "keep": true,
          "lift": 1.0,
          "count": 8,
          "avg_exit": 0,
          "avg_hold": 0,
          "advantage": 0
        },
        "PLUS30_PLUS75": {
          "keep": true,
          "lift": 1.0,
          "count": 7,
          "avg_exit": 0,
          "avg_hold": 0,
          "advantage": 0
        },
        "PLUS75_PLUS150": {
          "keep": true,
          "lift": 1.0,
          "count": 2,
          "avg_exit": 0,
          "avg_hold": 0,
          "advantage": 0
        },
        "PLUS150_PLUS300": {
          "keep": true,
          "lift": 1.0,
          "count": 0,
          "avg_exit": 0,
          "avg_hold": 0,
          "advantage": 0
        },
        "GT_PLUS300": {
          "keep": true,
          "lift": 1.0,
          "count": 0,
          "avg_exit": 0,
          "avg_hold": 0,
          "advantage": 0
        }
      },
      "DELTA_10S_30S": {
        "LT_MINUS20": {
          "keep": true,
          "lift": 1.0,
          "count": 1,
          "avg_exit": 0,
          "avg_hold": 0,
          "advantage": 0
        },
        "MINUS20_MINUS10": {
          "keep": true,
          "lift": 1.0,
          "count": 5,
          "avg_exit": 0,
          "avg_hold": 0,
          "advantage": 0
        },
        "MINUS10_MINUS3": {
          "keep": true,
          "lift": 1.0,
          "count": 7,
          "avg_exit": 0,
          "avg_hold": 0,
          "advantage": 0
        },
        "MINUS3_PLUS3": {
          "keep": true,
          "lift": 1.154,
          "count": 15,
          "avg_exit": 2.92,
          "avg_hold": 17.6,
          "advantage": -14.68
        },
        "PLUS3_PLUS10": {
          "keep": true,
          "lift": 1.0,
          "count": 8,
          "avg_exit": 0,
          "avg_hold": 0,
          "advantage": 0
        },
        "PLUS10_PLUS20": {
          "keep": true,
          "lift": 1.0,
          "count": 4,
          "avg_exit": 0,
          "avg_hold": 0,
          "advantage": 0
        },
        "GT_PLUS20": {
          "keep": true,
          "lift": 1.0,
          "count": 3,
          "avg_exit": 0,
          "avg_hold": 0,
          "advantage": 0
        }
      },
      "DELTA_30S_60S": {
        "LT_MINUS25": {
          "keep": true,
          "lift": 1.0,
          "count": 5,
          "avg_exit": 0,
          "avg_hold": 0,
          "advantage": 0
        },
        "MINUS25_MINUS10": {
          "keep": true,
          "lift": 1.0,
          "count": 5,
          "avg_exit": 0,
          "avg_hold": 0,
          "advantage": 0
        },
        "MINUS10_MINUS3": {
          "keep": true,
          "lift": 1.0,
          "count": 6,
          "avg_exit": 0,
          "avg_hold": 0,
          "advantage": 0
        },
        "MINUS3_PLUS3": {
          "keep": true,
          "lift": 1.0,
          "count": 12,
          "avg_exit": 0,
          "avg_hold": 0,
          "advantage": 0
        },
        "PLUS3_PLUS10": {
          "keep": true,
          "lift": 1.0,
          "count": 8,
          "avg_exit": 0,
          "avg_hold": 0,
          "advantage": 0
        },
        "PLUS10_PLUS25": {
          "keep": true,
          "lift": 1.0,
          "count": 4,
          "avg_exit": 0,
          "avg_hold": 0,
          "advantage": 0
        },
        "GT_PLUS25": {
          "keep": true,
          "lift": 1.0,
          "count": 3,
          "avg_exit": 0,
          "avg_hold": 0,
          "advantage": 0
        }
      },
      "DELTA_60S_5M": {
        "LT_MINUS40": {
          "keep": true,
          "lift": 1.0,
          "count": 11,
          "avg_exit": 0,
          "avg_hold": 0,
          "advantage": 0
        },
        "MINUS40_MINUS20": {
          "keep": true,
          "lift": 1.0,
          "count": 2,
          "avg_exit": 0,
          "avg_hold": 0,
          "advantage": 0
        },
        "MINUS20_MINUS5": {
          "keep": true,
          "lift": 1.0,
          "count": 5,
          "avg_exit": 0,
          "avg_hold": 0,
          "advantage": 0
        },
        "MINUS5_PLUS5": {
          "keep": true,
          "lift": 1.0,
          "count": 11,
          "avg_exit": 0,
          "avg_hold": 0,
          "advantage": 0
        },
        "PLUS5_PLUS20": {
          "keep": true,
          "lift": 1.0,
          "count": 8,
          "avg_exit": 0,
          "avg_hold": 0,
          "advantage": 0
        },
        "PLUS20_PLUS50": {
          "keep": true,
          "lift": 1.0,
          "count": 4,
          "avg_exit": 0,
          "avg_hold": 0,
          "advantage": 0
        },
        "GT_PLUS50": {
          "keep": true,
          "lift": 1.0,
          "count": 2,
          "avg_exit": 0,
          "avg_hold": 0,
          "advantage": 0
        }
      }
    }
  },
  "dry_run": false,
  "terminal": [
    "[02:31:00] \ud83d\udcca Mig:1078 Track:88 Upd:589690 Pos:0 SOL:$86.97",
    "[02:32:01] \ud83d\udcca Mig:1078 Track:88 Upd:591263 Pos:0 SOL:$86.96",
    "[02:33:02] \ud83d\udcca Mig:1078 Track:88 Upd:592800 Pos:0 SOL:$86.93",
    "[02:34:03] \ud83d\udcca Mig:1078 Track:88 Upd:594431 Pos:0 SOL:$86.90",
    "[02:35:03] \ud83d\udcca Mig:1078 Track:88 Upd:596049 Pos:0 SOL:$86.82",
    "[02:36:04] \ud83d\udcca Mig:1078 Track:88 Upd:597670 Pos:0 SOL:$86.79",
    "[02:37:05] \ud83d\udcca Mig:1078 Track:88 Upd:599338 Pos:0 SOL:$86.76",
    "[02:38:06] \ud83d\udcca Mig:1078 Track:88 Upd:600853 Pos:0 SOL:$86.81",
    "[02:39:07] \ud83d\udcca Mig:1078 Track:88 Upd:602346 Pos:0 SOL:$86.74",
    "[02:40:07] \ud83d\udcca Mig:1078 Track:88 Upd:603645 Pos:0 SOL:$86.74",
    "[02:41:08] \ud83d\udcca Mig:1078 Track:88 Upd:605175 Pos:0 SOL:$86.75",
    "[02:42:09] \ud83d\udcca Mig:1078 Track:88 Upd:606481 Pos:0 SOL:$86.77",
    "[02:43:10] \ud83d\udcca Mig:1078 Track:88 Upd:607724 Pos:0 SOL:$86.78",
    "[02:44:11] \ud83d\udcca Mig:1078 Track:88 Upd:608974 Pos:0 SOL:$86.78",
    "[02:45:11] \ud83d\udcca Mig:1078 Track:88 Upd:610270 Pos:0 SOL:$86.78",
    "[02:46:12] \ud83d\udcca Mig:1078 Track:88 Upd:611454 Pos:0 SOL:$86.78",
    "[02:47:13] \ud83d\udcca Mig:1078 Track:88 Upd:612734 Pos:0 SOL:$86.77",
    "[02:48:14] \ud83d\udcca Mig:1078 Track:88 Upd:613906 Pos:0 SOL:$86.79",
    "[02:49:15] \ud83d\udcca Mig:1078 Track:88 Upd:615206 Pos:0 SOL:$86.82",
    "[02:50:16] \ud83d\udcca Mig:1078 Track:88 Upd:616646 Pos:0 SOL:$86.85",
    "[02:51:16] \ud83d\udcca Mig:1078 Track:88 Upd:618060 Pos:0 SOL:$86.91",
    "[02:52:17] \ud83d\udcca Mig:1078 Track:88 Upd:619403 Pos:0 SOL:$86.94",
    "[02:53:18] \ud83d\udcca Mig:1078 Track:88 Upd:620632 Pos:0 SOL:$86.97",
    "[02:54:19] \ud83d\udcca Mig:1078 Track:88 Upd:621817 Pos:0 SOL:$86.99",
    "[02:55:20] \ud83d\udcca Mig:1078 Track:88 Upd:622936 Pos:0 SOL:$87.02",
    "[02:56:20] \ud83d\udcca Mig:1078 Track:88 Upd:624049 Pos:0 SOL:$87.01",
    "[02:57:21] \ud83d\udcca Mig:1078 Track:88 Upd:625171 Pos:0 SOL:$87.01",
    "[02:58:22] \ud83d\udcca Mig:1078 Track:88 Upd:626304 Pos:0 SOL:$87.02",
    "[02:59:23] \ud83d\udcca Mig:1078 Track:88 Upd:627398 Pos:0 SOL:$87.06",
    "[03:00:23] \ud83d\udcca Mig:1078 Track:88 Upd:628504 Pos:0 SOL:$87.09",
    "[03:01:24] \ud83d\udcca Mig:1078 Track:88 Upd:629565 Pos:0 SOL:$87.09",
    "[03:02:25] \ud83d\udcca Mig:1078 Track:88 Upd:630476 Pos:0 SOL:$87.08",
    "[03:03:26] \ud83d\udcca Mig:1078 Track:88 Upd:631480 Pos:0 SOL:$87.03",
    "[03:04:27] \ud83d\udcca Mig:1078 Track:88 Upd:632519 Pos:0 SOL:$87.03",
    "[03:05:27] \ud83d\udcca Mig:1078 Track:88 Upd:633780 Pos:0 SOL:$87.03",
    "[03:06:28] \ud83d\udcca Mig:1078 Track:88 Upd:635033 Pos:0 SOL:$86.93",
    "[03:07:29] \ud83d\udcca Mig:1078 Track:88 Upd:636181 Pos:0 SOL:$86.91",
    "[03:08:30] \ud83d\udcca Mig:1078 Track:88 Upd:637296 Pos:0 SOL:$86.88",
    "[03:09:31] \ud83d\udcca Mig:1078 Track:88 Upd:638448 Pos:0 SOL:$86.79",
    "[03:10:31] \ud83d\udcca Mig:1078 Track:88 Upd:639776 Pos:0 SOL:$86.71"
  ],
  "balance": {
    "start": 4.06455,
    "current": 0.0,
    "pnl_sol": -4.06455,
    "pnl_pct": -100.0
  },
  "trades": {
    "total": 0,
    "wins": 0,
    "losses": 0,
    "win_rate": 0
  },
  "positions": {
    "open": 0
  },
  "sol_price": 86.71,
  "bot_stats": {
    "migrations_seen": 1078,
    "migrations_added": 90,
    "pools_tracking": 88,
    "price_updates": 639842,
    "migrations_rejected": 0,
    "liquidity_rejected": 1,
    "bc_graduated": 91,
    "entries_found": 1,
    "buys_success": 0,
    "buys_failed": 1
  }
}