{
  "status": "live",
  "started_at": "2026-03-08T13:53:32.945026+00:00",
  "updated_at": "2026-03-09T06:32:09.359181+00:00",
  "uptime_seconds": 59916.4,
  "method": "ENV",
  "strategy": {},
  "dry_run": false,
  "terminal": [
    "[06:25:23] \ud83d\udd14 Migration #3120 detected",
    "[06:25:58] \ud83d\udd14 Migration #3121 detected",
    "[06:26:00] \ud83d\udd14 Migration #3122 detected",
    "[06:26:12] \u2705 BC Graduated: J68rQ6NPhREk\u2026",
    "[06:26:12] \ud83d\udce1 Tracking: J68rQ6NPhREkRbGQ\u2026 | Pool #1",
    "[06:26:12] \ud83d\udcca Mig:3122 Track:1 Upd:42991 Pos:0 SOL:$83.94",
    "[06:26:35] \ud83d\udd14 Migration #3123 detected",
    "[06:26:46] \ud83d\udd14 Migration #3124 detected",
    "[06:26:55] \ud83d\udd14 Migration #3125 detected",
    "[06:27:09] \u2705 BC Graduated: 5UERjPHdmjq9\u2026",
    "[06:27:09] \ud83d\udce1 Tracking: 5UERjPHdmjq9xwRD\u2026 | Pool #2",
    "[06:27:13] \ud83d\udcca Mig:3125 Track:2 Upd:43162 Pos:0 SOL:$83.93",
    "[06:27:19] \ud83d\udd14 Migration #3126 detected",
    "[06:27:21] \ud83d\udeab Disqualified: J68rQ6NPhREk\u2026 | max_time_without_entry | 1.2m",
    "[06:27:23] \ud83d\udd14 Migration #3127 detected",
    "[06:27:57] \ud83d\udd14 Migration #3128 detected",
    "[06:28:02] \ud83d\udd14 Migration #3129 detected",
    "[06:28:11] \ud83d\udeab Disqualified: 5UERjPHdmjq9\u2026 | max_time_without_entry | 1.0m",
    "[06:28:14] \ud83d\udcca Mig:3129 Track:0 Upd:43297 Pos:0 SOL:$83.94",
    "[06:28:36] \ud83d\udd14 Migration #3130 detected",
    "[06:28:42] \ud83d\udd14 Migration #3131 detected",
    "[06:29:15] \ud83d\udcca Mig:3131 Track:0 Upd:43297 Pos:0 SOL:$83.92",
    "[06:29:35] \ud83d\udd14 Migration #3132 detected",
    "[06:29:40] \ud83d\udd14 Migration #3133 detected",
    "[06:29:43] \ud83d\udd14 Migration #3134 detected",
    "[06:29:44] \ud83d\udd14 Migration #3135 detected",
    "[06:29:58] \ud83d\udd14 Migration #3136 detected",
    "[06:30:16] \ud83d\udcca Mig:3136 Track:0 Upd:43297 Pos:0 SOL:$83.92",
    "[06:30:22] \ud83d\udd14 Migration #3137 detected",
    "[06:30:24] \ud83d\udd14 Migration #3138 detected",
    "[06:30:37] \ud83d\udd14 Migration #3139 detected",
    "[06:30:42] \ud83d\udd14 Migration #3140 detected",
    "[06:30:55] \u2705 BC Graduated: Cc7tKYzqrYV9\u2026",
    "[06:30:55] \ud83d\udce1 Tracking: Cc7tKYzqrYV9ZXi1\u2026 | Pool #1",
    "[06:31:17] \ud83d\udcca Mig:3140 Track:1 Upd:43363 Pos:0 SOL:$83.86",
    "[06:31:19] \ud83d\udd14 Migration #3141 detected",
    "[06:31:22] \ud83d\udd14 Migration #3142 detected",
    "[06:31:36] \ud83d\udd14 Migration #3143 detected",
    "[06:31:46] \ud83d\udd14 Migration #3144 detected",
    "[06:32:01] \ud83d\udeab Disqualified: Cc7tKYzqrYV9\u2026 | max_time_without_entry | 1.1m"
  ],
  "balance": {
    "start": 3.826566,
    "current": 3.284376,
    "pnl_sol": -0.54219,
    "pnl_pct": -14.17
  },
  "trades": {
    "total": 0,
    "wins": 0,
    "losses": 0,
    "win_rate": 0
  },
  "positions": {
    "open": 0
  },
  "sol_price": 83.86,
  "bot_stats": {
    "migrations_seen": 3144,
    "migrations_added": 203,
    "pools_tracking": 0,
    "price_updates": 43498,
    "migrations_rejected": 0,
    "liquidity_rejected": 7,
    "bc_graduated": 210,
    "entries_found": 0,
    "buys_success": 0,
    "buys_failed": 0
  }
}