{
  "status": "live",
  "started_at": "2026-03-05T15:03:09.438974+00:00",
  "updated_at": "2026-03-05T15:22:33.831049+00:00",
  "uptime_seconds": 1164.4,
  "method": "ENV",
  "strategy": {},
  "dry_run": false,
  "terminal": [
    "[15:13:18] \ud83d\udd14 Migration #33 detected",
    "[15:13:19] \ud83d\udcca Mig:33 Track:0 Upd:118 Pos:0 SOL:$90.18",
    "[15:13:29] \ud83d\udd14 Migration #34 detected",
    "[15:13:48] \ud83d\udd14 Migration #35 detected",
    "[15:14:20] \ud83d\udcca Mig:35 Track:0 Upd:118 Pos:0 SOL:$89.94",
    "[15:14:22] \ud83d\udd14 Migration #36 detected",
    "[15:14:44] \ud83d\udd14 Migration #37 detected",
    "[15:14:48] \ud83d\udd14 Migration #38 detected",
    "[15:15:21] \ud83d\udcca Mig:38 Track:0 Upd:118 Pos:0 SOL:$89.92",
    "[15:15:25] \ud83d\udd14 Migration #39 detected",
    "[15:15:39] \ud83d\udd14 Migration #40 detected",
    "[15:15:48] \ud83d\udd14 Migration #41 detected",
    "[15:15:49] \ud83d\udd14 Migration #42 detected",
    "[15:15:53] \u2705 BC Graduated: 7rXfqefV28Vk\u2026",
    "[15:15:53] \ud83d\udce1 Tracking: 7rXfqefV28VkJ1BK\u2026 | Pool #1",
    "[15:16:04] \ud83d\udd14 Migration #43 detected",
    "[15:16:22] \ud83d\udcca Mig:43 Track:1 Upd:204 Pos:0 SOL:$89.90",
    "[15:16:55] \ud83d\udeab Disqualified: 7rXfqefV28Vk\u2026 | max_time_without_entry | 1.0m",
    "[15:16:57] \ud83d\udd14 Migration #44 detected",
    "[15:17:24] \ud83d\udcca Mig:44 Track:0 Upd:288 Pos:0 SOL:$89.88",
    "[15:17:44] \ud83d\udd14 Migration #45 detected",
    "[15:18:12] \ud83d\udd14 Migration #46 detected",
    "[15:18:20] \ud83d\udd14 Migration #47 detected",
    "[15:18:25] \ud83d\udcca Mig:47 Track:0 Upd:288 Pos:0 SOL:$89.79",
    "[15:18:47] \ud83d\udd14 Migration #48 detected",
    "[15:18:59] \ud83d\udd14 Migration #49 detected",
    "[15:19:01] \ud83d\udd14 Migration #50 detected",
    "[15:19:16] \u2705 BC Graduated: 3U7ngzAaoPwy\u2026",
    "[15:19:16] \ud83d\udce1 Tracking: 3U7ngzAaoPwyQC7D\u2026 | Pool #1",
    "[15:19:26] \ud83d\udcca Mig:50 Track:1 Upd:314 Pos:0 SOL:$89.74",
    "[15:19:48] \ud83d\udd14 Migration #51 detected",
    "[15:20:00] \ud83d\udd14 Migration #52 detected",
    "[15:20:24] \ud83d\udd14 Migration #53 detected",
    "[15:20:25] \ud83d\udeab Disqualified: 3U7ngzAaoPwy\u2026 | max_time_without_entry | 1.1m",
    "[15:20:28] \ud83d\udcca Mig:53 Track:0 Upd:509 Pos:0 SOL:$89.70",
    "[15:21:27] \ud83d\udd14 Migration #54 detected",
    "[15:21:29] \ud83d\udcca Mig:54 Track:0 Upd:509 Pos:0 SOL:$89.69",
    "[15:22:04] \ud83d\udd14 Migration #55 detected",
    "[15:22:23] \ud83d\udd14 Migration #56 detected",
    "[15:22:30] \ud83d\udcca Mig:56 Track:0 Upd:509 Pos:0 SOL:$89.71"
  ],
  "balance": {
    "start": 4.158328,
    "current": 4.158328,
    "pnl_sol": 0.0,
    "pnl_pct": 0.0
  },
  "trades": {
    "total": 0,
    "wins": 0,
    "losses": 0,
    "win_rate": 0
  },
  "positions": {
    "open": 0
  },
  "sol_price": 89.71,
  "bot_stats": {
    "migrations_seen": 56,
    "migrations_added": 3,
    "pools_tracking": 0,
    "price_updates": 509,
    "migrations_rejected": 0,
    "liquidity_rejected": 0,
    "bc_graduated": 3,
    "entries_found": 0,
    "buys_success": 0,
    "buys_failed": 0
  }
}